Zeitgleich/FormatChecks.py
Zeitgleich/MultiOriginTimeSeries.py
Zeitgleich/Origin.py
Zeitgleich/TimeSeriesData.py
Zeitgleich/TimestampFormat.py
Zeitgleich/__init__.py
zeitgleich-0.1.4.dist-info/METADATA
zeitgleich-0.1.4.dist-info/WHEEL
zeitgleich-0.1.4.dist-info/licenses/LICENSE
zeitgleich-0.1.4.dist-info/RECORD
