Metadata-Version: 2.4
Name: Zeitgleich
Version: 0.1.4
Summary: Zeitgleich is a time series library for handling data and timestamps with origins. It provides a way to manage time series data, validate formats, and perform operations on time series data while maintaining origin information.
Author-email: Jakob Friedl <jakob.friedl@tuwien.ac.at>
License-Expression: MIT
License-File: LICENSE
Keywords: conversion,origin,time series,timestamp,timezone
Classifier: Development Status :: 2 - Pre-Alpha
Classifier: Intended Audience :: Developers
Classifier: License :: OSI Approved :: MIT License
Classifier: Operating System :: OS Independent
Classifier: Programming Language :: Python :: 3
Classifier: Programming Language :: Python :: 3.6
Classifier: Programming Language :: Python :: 3.7
Classifier: Programming Language :: Python :: 3.8
Classifier: Programming Language :: Python :: 3.9
Requires-Python: >=3.6
Requires-Dist: pandas
